[
    {
      "ProductName": "Chubby Doll House Set",
      "ProductID": "ZX82",
      "ProductPrice": "$3.20",
      "ProductDescription": "Strange looking gum",
      "ProductCategory": "Toy"
    },
    {
      "ProductName": "Greenoc Action Figure",
      "ProductID": "BJ21",
      "ProductPrice": "$3.20",
      "ProductDescription": "Strange looking gum",
      "ProductCategory": "Toy"
    },
    {
      "ProductName": "Benjamin Wood Axe Toy",
      "ProductID": "SJ82",
      "ProductPrice": "$3.20",
      "ProductDescription": "Strange looking gum",
      "ProductCategory": "Toy"
    },
    {
      "ProductName": "Horse Magnifier Glass",
      "ProductID": "IX21",
      "ProductPrice": "$3.20",
      "ProductDescription": "Strange looking gum",
      "ProductCategory": "Toy"
    }
  ]